{"cameraMode":{"drawMode":0,"name":"Shaded","section":"Shading Mode"},"sceneLighting":true,"audioPlay":false,"sceneViewState":{"m_AlwaysRefresh":false,"showFog":false,"showSkybox":true,"showFlares":true,"showImageEffects":true,"showParticleSystems":true,"showVisualEffectGraphs":true,"m_FxEnabled":true},"in2DMode":false,"pivot":{"x":111.95077514648438,"y":-7.442132949829102,"z":135.774169921875},"rotation":{"x":0.06372437626123429,"y":-0.9139337539672852,"z":0.158114954829216,"w":0.3683326840400696},"size":33.806434631347659,"orthographic":false}